{
  "table": "programs",
  "fields": [
    {
      "name": "program_id",
      "type": "INT",
      "options": [ "NOT NULL", "AUTO_INCREMENT" ]
    },
    {
      "name": "name",
      "type": "VARCHAR(30)",
      "options": [ "NOT NULL" ]
    },
    {
      "name": "is_certified",
      "type": "BOOLEAN",
      "options": [ "NOT NULL" ]
    },
    {
      "name": "is_remote",
      "type": "BOOLEAN",
      "options": [ "NOT NULL" ]
    },
    {
      "name": "start_date",
      "type": "DATE",
      "options": [ "NOT NULL" ]
    },
    {
      "name": "end_date",
      "type": "DATE",
      "options": [ "NOT NULL" ]
    },
    {
      "name": "description",
      "type": "VARCHAR(120)",
      "options": []
    },
    {
      "name": "min_semester",
      "type": "INT",
      "options": [ "NOT NULL" ]
    },
    {
      "name": "sks",
      "type": "INT",
      "options": [ "NOT NULL" ]
    },
    {
      "name": "program_type_id",
      "type": "INT",
      "options": [ "NOT NULL" ]
    },
    {
      "name": "agency_id",
      "type": "INT",
      "options": [ "NOT NULL" ]
    }
  ],
  "primary": [ "program_id" ],
  "unique": [],
  "foreign": [
    { "key": "program_type_id", "ref": "program_types" },
    { "key": "agency_id", "ref": "agencies" }
  ]
}